poetry_lock_groups/ExtendedLockCommand.py
poetry_lock_groups/__init__.py
poetry_lock_groups/plugin.py
poetry_lock_groups_plugin-1.0.2.dist-info/entry_points.txt
poetry_lock_groups_plugin-1.0.2.dist-info/WHEEL
poetry_lock_groups_plugin-1.0.2.dist-info/METADATA
poetry_lock_groups_plugin-1.0.2.dist-info/RECORD
