Metadata-Version: 2.1
Name: poetry-lock-groups-plugin
Version: 1.0.2
Summary: Poetry extension enabling group dependency application at the lock stage
Home-page: https://bitbucket.org/cpointe/poetry-lock-groups-plugin
License: MIT
Author: Peter Jablonski
Author-email: jablonski_peter@bah.com
Requires-Python: >=3.7,<4.0
Classifier: License :: OSI Approved :: MIT License
Classifier: Programming Language :: Python :: 3
Classifier: Programming Language :: Python :: 3.7
Classifier: Programming Language :: Python :: 3.8
Classifier: Programming Language :: Python :: 3.9
Classifier: Programming Language :: Python :: 3.10
Requires-Dist: black (>=22.8.0,<23.0.0)
Requires-Dist: poetry (>=1.2.1,<2.0.0)
Project-URL: Repository, https://bitbucket.org/cpointe/poetry-lock-groups-plugin
